<!DOCTYPE frameset SYSTEM "frameset.dtd">
<frameset>
	<predicate lemma="dictation">
		<roleset framnet="" id="dictation.01" name="Imposing, commanding, deciding" source="verb-dictate.01" vncls="37.1.1">
			<roles>
				<role descr="Dictator, agent" f="PAG" n="0">
					<vnrole vncls="37.1.1" vntheta="Agent"/>
				</role>
				<role descr="Message, command dictated" f="PPT" n="1">
					<vnrole vncls="37.1.1" vntheta="Topic"/>
				</role>
				<role descr="Listened, dictated-to" f="GOL" n="2">
					<vnrole vncls="37.1.1" vntheta="Recipient"/>
				</role>
				<note/>
			</roles>
			<example name="All args" src="" type="">
				<inflection aspect="ns" form="ns" person="ns" tense="ns" voice="ns"/>
				<text>
					The General's dictation to the troops that they immediately prepare for battle was obeyed.
				</text>
				<arg f="" n="0">
					The General's
				</arg>
				<rel f="">
					dictation
				</rel>
				<arg f="" n="2">
					to the troops
				</arg>
				<arg f="" n="1">
					that they immediately prepare for battle
				</arg>
				<note/>
			</example>
			<note>
				dictate.01
			</note>
		</roleset>
		<roleset framnet="" id="dictation.02" name="Speaking aloud for someone to write down" source="verb-speak.01" vncls="">
			<roles>
				<role descr="Speaker" f="PAG" n="0"/>
				<role descr="Utterance" f="PPT" n="1"/>
				<role descr="Hearer, recorder" f="" n="2"/>
				<note/>
			</roles>
			<example name="Arg0, 1" src="" type="">
				<inflection aspect="ns" form="ns" person="ns" tense="ns" voice="ns"/>
				<text>
					The doctor's dictation of her notes was later transcribed by her secretary.
				</text>
				<arg f="" n="0">
					The doctor's
				</arg>
				<rel f="">
					dictation
				</rel>
				<arg f="" n="1">
					of her notes
				</arg>
				<note/>
			</example>
			<note/>
		</roleset>
		<note/>
	</predicate>
	<note/>
</frameset>
